[
    {
        "position": -5,
        "layer": 12,
        "refusal_score": -9.855093002319336,
        "steering_score": 7.675726890563965,
        "kl_div_score": 0.05881983861131122
    },
    {
        "position": -2,
        "layer": 12,
        "refusal_score": -9.587724685668945,
        "steering_score": 7.961967468261719,
        "kl_div_score": 0.025750730835997937
    },
    {
        "position": -1,
        "layer": 12,
        "refusal_score": -9.223579406738281,
        "steering_score": 9.129658699035645,
        "kl_div_score": 0.027542884156896787
    },
    {
        "position": -3,
        "layer": 12,
        "refusal_score": -9.136280059814453,
        "steering_score": 3.1545984745025635,
        "kl_div_score": 0.07512889460010282
    },
    {
        "position": -5,
        "layer": 13,
        "refusal_score": -8.753713607788086,
        "steering_score": 7.360633373260498,
        "kl_div_score": 0.060254739766449926
    },
    {
        "position": -2,
        "layer": 11,
        "refusal_score": -8.694852828979492,
        "steering_score": 8.986674308776855,
        "kl_div_score": 0.02278770061256304
    },
    {
        "position": -1,
        "layer": 11,
        "refusal_score": -8.252202987670898,
        "steering_score": 9.371790885925293,
        "kl_div_score": 0.04419264166291458
    },
    {
        "position": -5,
        "layer": 11,
        "refusal_score": -7.7250776290893555,
        "steering_score": 7.864079475402832,
        "kl_div_score": 0.030278851214323825
    },
    {
        "position": -3,
        "layer": 11,
        "refusal_score": -7.17034387588501,
        "steering_score": 0.10405318439006805,
        "kl_div_score": 0.026158523687212505
    },
    {
        "position": -1,
        "layer": 10,
        "refusal_score": -6.343708038330078,
        "steering_score": 5.8779215812683105,
        "kl_div_score": 0.08968460783118479
    },
    {
        "position": -5,
        "layer": 10,
        "refusal_score": -4.951752662658691,
        "steering_score": 7.707437515258789,
        "kl_div_score": 0.041992868817351994
    },
    {
        "position": -5,
        "layer": 9,
        "refusal_score": -4.097323894500732,
        "steering_score": 3.176412582397461,
        "kl_div_score": 0.05483962199769142
    },
    {
        "position": -2,
        "layer": 10,
        "refusal_score": -3.8918004035949707,
        "steering_score": 1.264135479927063,
        "kl_div_score": 0.04128143067758505
    },
    {
        "position": -5,
        "layer": 16,
        "refusal_score": -2.293829917907715,
        "steering_score": 2.5993306636810303,
        "kl_div_score": 0.08620592815454689
    },
    {
        "position": -3,
        "layer": 14,
        "refusal_score": -1.8188115358352661,
        "steering_score": 5.905934810638428,
        "kl_div_score": 0.013582281991189495
    },
    {
        "position": -3,
        "layer": 15,
        "refusal_score": -0.5254128575325012,
        "steering_score": 6.762792587280273,
        "kl_div_score": 0.07483821471900672
    },
    {
        "position": -1,
        "layer": 13,
        "refusal_score": -0.21367457509040833,
        "steering_score": 5.670637607574463,
        "kl_div_score": 0.031769845311828596
    },
    {
        "position": -3,
        "layer": 19,
        "refusal_score": 1.393025279045105,
        "steering_score": 0.7602143883705139,
        "kl_div_score": 0.08757015665294422
    },
    {
        "position": -3,
        "layer": 20,
        "refusal_score": 1.5026053190231323,
        "steering_score": 0.9795277118682861,
        "kl_div_score": 0.08319689828526813
    },
    {
        "position": -2,
        "layer": 13,
        "refusal_score": 1.5072500705718994,
        "steering_score": 6.431893825531006,
        "kl_div_score": 0.007337516863975353
    },
    {
        "position": -3,
        "layer": 21,
        "refusal_score": 2.769855499267578,
        "steering_score": 0.5267502069473267,
        "kl_div_score": 0.08146600194147086
    },
    {
        "position": -3,
        "layer": 22,
        "refusal_score": 3.177785634994507,
        "steering_score": 0.2288963794708252,
        "kl_div_score": 0.07539794459837941
    },
    {
        "position": -4,
        "layer": 13,
        "refusal_score": 3.653780937194824,
        "steering_score": 2.1125099658966064,
        "kl_div_score": 0.08487860439893934
    },
    {
        "position": -4,
        "layer": 10,
        "refusal_score": 5.724307060241699,
        "steering_score": 4.685765266418457,
        "kl_div_score": 0.09746260263764356
    },
    {
        "position": -4,
        "layer": 11,
        "refusal_score": 6.058686256408691,
        "steering_score": 3.4397318363189697,
        "kl_div_score": 0.09495813922764175
    }
]